tfrecorder/__init__.py
tfrecorder/accessor.py
tfrecorder/accessor_test.py
tfrecorder/beam_image.py
tfrecorder/beam_image_test.py
tfrecorder/beam_pipeline.py
tfrecorder/beam_pipeline_test.py
tfrecorder/cli.py
tfrecorder/constants.py
tfrecorder/converter.py
tfrecorder/converter_test.py
tfrecorder/dataset_loader.py
tfrecorder/dataset_loader_test.py
tfrecorder/input_schema.py
tfrecorder/input_schema_test.py
tfrecorder/test_utils.py
tfrecorder/types.py
tfrecorder/utils.py
tfrecorder/utils_test.py
tfrecorder-2.0.dist-info/LICENSE
tfrecorder-2.0.dist-info/METADATA
tfrecorder-2.0.dist-info/WHEEL
tfrecorder-2.0.dist-info/entry_points.txt
tfrecorder-2.0.dist-info/top_level.txt
tfrecorder-2.0.dist-info/RECORD
