Metadata-Version: 2.1
Name: tfrecorder
Version: 2.0
Summary: TFRecorder creates TensorFlow Records easily.
Home-page: UNKNOWN
Author: UNKNOWN
Author-email: UNKNOWN
License: UNKNOWN
Platform: UNKNOWN
Requires-Dist: apache-beam[gcp] (>=2.22.0)
Requires-Dist: avro (>=1.10.0)
Requires-Dist: coverage (>=5.1)
Requires-Dist: ipython (>=7.15.0)
Requires-Dist: fire (>=0.3.1)
Requires-Dist: frozendict (>=1.2)
Requires-Dist: nose (>=1.3.7)
Requires-Dist: numpy (<1.19.0)
Requires-Dist: pandas (>=1.0.4)
Requires-Dist: Pillow (>=7.1.2)
Requires-Dist: pyarrow (<0.18.0,>=0.17)
Requires-Dist: pylint (>=2.5.3)
Requires-Dist: pytz (>=2020.1)
Requires-Dist: python-dateutil
Requires-Dist: tensorflow (==2.3.1)
Requires-Dist: tensorflow-transform (>=0.22)
